stockkly_repo/__init__.py
stockkly_repo/pricesBusiness.py
stockkly_repo-0.1.9.dist-info/LICENSE
stockkly_repo-0.1.9.dist-info/METADATA
stockkly_repo-0.1.9.dist-info/WHEEL
stockkly_repo-0.1.9.dist-info/top_level.txt
stockkly_repo-0.1.9.dist-info/RECORD
